LICENSE
MANIFEST.in
README.md
setup.cfg
setup.py
alphaz/README.md
alphaz/__init__.py
alphaz/alphaz.bat
alphaz/alphaz.code-workspace
alphaz/alphaz.sh
alphaz/api.bat
alphaz/api.json
alphaz/api.py
alphaz/config.json
alphaz/core.py
alphaz/git.sh
alphaz/help.md
alphaz/index.html
alphaz/reload_gitignore.bat
alphaz/req.sh
alphaz/requirements.txt
alphaz/run.py
alphaz/test.py
alphaz.egg-info/PKG-INFO
alphaz.egg-info/SOURCES.txt
alphaz.egg-info/dependency_links.txt
alphaz.egg-info/requires.txt
alphaz.egg-info/top_level.txt
alphaz/apis/__init__.py
alphaz/apis/log.py
alphaz/apis/mails.py
alphaz/apis/tests.py
alphaz/apis/routes/__init__.py
alphaz/apis/routes/admin.py
alphaz/apis/routes/api.py
alphaz/apis/routes/basic_tests.py
alphaz/apis/routes/database.py
alphaz/apis/routes/git.py
alphaz/apis/routes/logs.py
alphaz/apis/routes/mails.py
alphaz/apis/routes/main.py
alphaz/apis/routes/tests.py
alphaz/apis/routes/users.py
alphaz/apis/routes/user_management/__init__.py
alphaz/apis/routes/user_management/application_management.py
alphaz/apis/routes/user_management/permission_management.py
alphaz/apis/routes/user_management/role_management.py
alphaz/apis/routes/user_management/user_management.py
alphaz/apis/users/__init__.py
alphaz/apis/users/ldap.py
alphaz/apis/users/users.py
alphaz/config/__init__.py
alphaz/config/config.css
alphaz/config/config.html
alphaz/config/main_configuration.py
alphaz/config/page.py
alphaz/config/source.html
alphaz/documentations/mkdocs.yml
alphaz/documentations/docs/alpha_admin.md
alphaz/documentations/docs/alpha_core.md
alphaz/documentations/docs/alpha_screens.md
alphaz/documentations/docs/alpha_setup.md
alphaz/documentations/docs/api_database.md
alphaz/documentations/docs/configuration.md
alphaz/documentations/docs/documentation.md
alphaz/documentations/docs/index.md
alphaz/documentations/docs/api/authorizations.md
alphaz/documentations/docs/api/cache.md
alphaz/documentations/docs/api/configuration.md
alphaz/documentations/docs/api/issues.md
alphaz/documentations/docs/api/main.md
alphaz/documentations/docs/api/methods.md
alphaz/documentations/docs/api/parameters.md
