Metadata-Version: 2.1
Name: alphaz
Version: 0.7.8.8
Summary: A package full of very nice tools
Home-page: https://github.com/ZAurele/alphaz
Download-URL: https://github.com/ZAurele/alphaz/archive/refs/tags/0.7.8.8.tar.gz
Author: Aurèle
Author-email: contact@aurele.eu
License: MIT
Keywords: Flask,Json
Platform: UNKNOWN
Classifier: Development Status :: 3 - Alpha
Classifier: Intended Audience :: Developers
Classifier: Topic :: Software Development :: Build Tools
Classifier: License :: OSI Approved :: MIT License
Classifier: Programming Language :: Python :: 3.10
License-File: LICENSE
